diffprivlib/__init__.py
diffprivlib/accountant.py
diffprivlib/utils.py
diffprivlib/validation.py
diffprivlib/mechanisms/__init__.py
diffprivlib/mechanisms/base.py
diffprivlib/mechanisms/binary.py
diffprivlib/mechanisms/bingham.py
diffprivlib/mechanisms/exponential.py
diffprivlib/mechanisms/gaussian.py
diffprivlib/mechanisms/geometric.py
diffprivlib/mechanisms/laplace.py
diffprivlib/mechanisms/snapping.py
diffprivlib/mechanisms/staircase.py
diffprivlib/mechanisms/uniform.py
diffprivlib/mechanisms/vector.py
diffprivlib/mechanisms/transforms/__init__.py
diffprivlib/mechanisms/transforms/base.py
diffprivlib/mechanisms/transforms/inttostring.py
diffprivlib/mechanisms/transforms/roundedinteger.py
diffprivlib/mechanisms/transforms/stringtoint.py
diffprivlib/models/__init__.py
diffprivlib/models/forest.py
diffprivlib/models/k_means.py
diffprivlib/models/linear_regression.py
diffprivlib/models/logistic_regression.py
diffprivlib/models/naive_bayes.py
diffprivlib/models/pca.py
diffprivlib/models/standard_scaler.py
diffprivlib/models/utils.py
diffprivlib/tools/__init__.py
diffprivlib/tools/histograms.py
diffprivlib/tools/quantiles.py
diffprivlib/tools/utils.py
tests/__init__.py
tests/test_Budget.py
tests/test_BudgetAccountant.py
tests/test_check_bounds.py
tests/test_check_epsilon_delta.py
tests/test_check_random_state.py
tests/test_clip_to_bounds.py
tests/test_clip_to_norm.py
tests/mechanisms/__init__.py
tests/mechanisms/test_BernoulliNegExp.py
tests/mechanisms/test_Binary.py
tests/mechanisms/test_Bingham.py
tests/mechanisms/test_DPMachine.py
tests/mechanisms/test_DPMechanism.py
tests/mechanisms/test_Exponential.py
tests/mechanisms/test_ExponentialCategorical.py
tests/mechanisms/test_ExponentialHierarchical.py
tests/mechanisms/test_Gaussian.py
tests/mechanisms/test_GaussianAnalytic.py
tests/mechanisms/test_GaussianDiscrete.py
tests/mechanisms/test_Geometric.py
tests/mechanisms/test_GeometricFolded.py
tests/mechanisms/test_GeometricTruncated.py
tests/mechanisms/test_Laplace.py
diffprivlib-0.6.5.dist-info/LICENSE.md
diffprivlib-0.6.5.dist-info/METADATA
diffprivlib-0.6.5.dist-info/WHEEL
diffprivlib-0.6.5.dist-info/top_level.txt
diffprivlib-0.6.5.dist-info/RECORD
