Metadata-Version: 2.1
Name: diffprivlib
Version: 0.6.5
Summary: IBM Differential Privacy Library
Home-page: https://github.com/IBM/differential-privacy-library
Author: Naoise Holohan
Author-email: naoise.holohan@ibm.com
License: MIT
Classifier: Development Status :: 4 - Beta
Classifier: Intended Audience :: Developers
Classifier: Intended Audience :: Education
Classifier: Intended Audience :: Science/Research
Classifier: License :: OSI Approved
Classifier: License :: OSI Approved :: MIT License
Classifier: Natural Language :: English
Classifier: Programming Language :: Python :: 3
Classifier: Programming Language :: Python :: 3 :: Only
Classifier: Programming Language :: Python :: 3.8
Classifier: Programming Language :: Python :: 3.9
Classifier: Programming Language :: Python :: 3.10
Classifier: Programming Language :: Python :: 3.11
Classifier: Programming Language :: Python :: 3.12
Classifier: Topic :: Software Development :: Libraries
Classifier: Topic :: Software Development :: Libraries :: Python Modules
Classifier: Topic :: Scientific/Engineering
Classifier: Topic :: Security
Requires-Python: >=3.8
License-File: LICENSE.md
Requires-Dist: numpy>=1.21.6
Requires-Dist: scikit-learn>=0.24.2
Requires-Dist: scipy>=1.7.3
Requires-Dist: joblib>=0.16.0
Requires-Dist: setuptools>=49.0.0
Provides-Extra: docs
Requires-Dist: sphinx>=5.0; extra == "docs"
Requires-Dist: sphinx_rtd_theme>=1.3; extra == "docs"
Provides-Extra: crlibm
Requires-Dist: crlibm; extra == "crlibm"
